client_dercaci.py
client_dercaci-1.0.0.dist-info/WHEEL
client_dercaci-1.0.0.dist-info/METADATA
client_dercaci-1.0.0.dist-info/RECORD
