Metadata-Version: 2.1
Name: client-dercaci
Version: 1.0.0
Summary: " Client json ==> server ==> modified json "
Author: Vitlie
Author-email: dercaci200@gmail.com
Requires-Python: >=3.6,<4.0
Classifier: Programming Language :: Python :: 3
Classifier: Programming Language :: Python :: 3.10
Classifier: Programming Language :: Python :: 3.6
Classifier: Programming Language :: Python :: 3.7
Classifier: Programming Language :: Python :: 3.8
Classifier: Programming Language :: Python :: 3.9
